nomenclators_archetype/domain/__init__.py
nomenclators_archetype/domain/commons.py
nomenclators_archetype/domain/exceptions.py
nomenclators_archetype/domain/loggers.py
nomenclators_archetype/domain/mapper/__init__.py
nomenclators_archetype/domain/mapper/commons.py
nomenclators_archetype/domain/repository/__init__.py
nomenclators_archetype/domain/repository/builders.py
nomenclators_archetype/domain/repository/commons.py
nomenclators_archetype/domain/service/commons.py
nomenclators_archetype/domain/usecase/commons.py
nomenclators_archetype/domain/validator/__init__.py
nomenclators_archetype/domain/validator/commons.py
nomenclators_archetype/infrastructure/__init__.py
nomenclators_archetype/infrastructure/db/__init__.py
nomenclators_archetype/infrastructure/db/builders.py
nomenclators_archetype/infrastructure/db/commons.py
nomenclators_archetype/infrastructure/db/repository.py
nomenclators_archetype/infrastructure/db/usecases.py
nomenclators_archetype/infrastructure/db/validators.py
nomenclators_archetype/infrastructure/http/__init__.py
nomenclators_archetype/infrastructure/http/auths.py
nomenclators_archetype/infrastructure/http/exceptions.py
nomenclators_archetype/infrastructure/http/loggers.py
nomenclators_archetype/infrastructure/http/mappers.py
nomenclators_archetype/infrastructure/http/routers.py
nomenclators_archetype/infrastructure/http/schemas.py
nomenclators_elprat-0.1.9.dist-info/licenses/LICENSE
nomenclators_elprat-0.1.9.dist-info/METADATA
nomenclators_elprat-0.1.9.dist-info/WHEEL
nomenclators_elprat-0.1.9.dist-info/top_level.txt
nomenclators_elprat-0.1.9.dist-info/RECORD
